unique_user_email/__init__.py
unique_user_email/apps.py
unique_user_email/backend.py
unique_user_email/forms.py
unique_user_email/models.py
unique_user_email/migrations/0001_initial.py
unique_user_email/migrations/__init__.py
django_unique_user_email-23.2.dist-info/LICENSE
django_unique_user_email-23.2.dist-info/WHEEL
django_unique_user_email-23.2.dist-info/METADATA
django_unique_user_email-23.2.dist-info/RECORD
