Metadata-Version: 2.1
Name: django-unique-user-email
Version: 23.2
Summary: django-unique-user-email
Author-email: Carlton Gibson <carlton.gibson@noumenal.es>
Classifier: License :: OSI Approved :: MIT License
Requires-Dist: Django>=4.2
Project-URL: Home, https://noumenal.es/unique_user_email/
